[
 {
   "NAVAREA": "I",
   "Broadcast frequency (kHz)": 518,
   "NAVTEX CRS name": "Svalbard",
   "NAVTEX CRS identifier": "A",
   "Country": "Norway",
   "Latitude": "78° 02' N",
   "Longitude": "13° 40' E",
   "Broadcast range (NM)": "450",
   "Transmission times (All in UTC)": "0000, 0400, 0800, 1200, 1600, 2000",
   "Broadcast language": "English"
 },
 {
   "NAVAREA": "I",
   "Broadcast frequency (kHz)": 518,
   "NAVTEX CRS name": "Bodø",
   "NAVTEX CRS identifier": "B",
   "Country": "Norway",
   "Latitude": "67° 16' N",
   "Longitude": "14° 23' E",
   "Broadcast range (NM)": "450",
   "Transmission times (All in UTC)": "0010, 0410, 0810, 1210, 1610, 2010",
   "Broadcast language": "English"
 },
 {
   "NAVAREA": "I",
   "Broadcast frequency (kHz)": 518,
   "NAVTEX CRS name": "Murmansk",
   "NAVTEX CRS identifier": "C",
   "Country": "Russia",
   "Latitude": "68° 46' N",
   "Longitude": "32° 58' E",
   "Broadcast range (NM)": "140",
   "Transmission times (All in UTC)": "0020, 0420, 0820, 1220, 1620, 2020",
   "Broadcast language": "English"
 },
 {
   "NAVAREA": "I",
   "Broadcast frequency (kHz)": 518,
   "NAVTEX CRS name": "Tórshavn",
   "NAVTEX CRS identifier": "D",
   "Country": "Denmark",
   "Latitude": "62° 01' N",
   "Longitude": "06° 48' E",
   "Broadcast range (NM)": "250",
   "Transmission times (All in UTC)": "0030, 0430, 0830, 1230, 1630, 2030",
   "Broadcast language": "English"
 },
 {
   "NAVAREA": "I",
   "Broadcast frequency (kHz)": 518,
   "NAVTEX CRS name": "Niton",
   "NAVTEX CRS identifier": "E",
   "Country": "England",
   "Latitude": "50° 35' N",
   "Longitude": "01° 18' W",
   "Broadcast range (NM)": "270",
   "Transmission times (All in UTC)": "0040, 0440, 0840, 1240, 1640, 2040",
   "Broadcast language": "English"
 },
 {
   "NAVAREA": "I",
   "Broadcast frequency (kHz)": 518,
   "NAVTEX CRS name": "Arkhangelsk",
   "NAVTEX CRS identifier": "F",
   "Country": "Russia",
   "Latitude": "64° 33' N",
   "Longitude": "40° 32' E",
   "Broadcast range (NM)": "280",
   "Transmission times (All in UTC)": "0050, 0450, 0850, 1250, 1650, 2050",
   "Broadcast language": "English"
 },
 {
   "NAVAREA": "I",
   "Broadcast frequency (kHz)": 518,
   "NAVTEX CRS name": "Cullercoats",
   "NAVTEX CRS identifier": "G",
   "Country": "England",
   "Latitude": "55° 04' N",
   "Longitude": "01° 28' W",
   "Broadcast range (NM)": "270",
   "Transmission times (All in UTC)": "0100, 0500, 0900, 1300, 1700, 2100",
   "Broadcast language": "English"
 },
 {
   "NAVAREA": "I",
   "Broadcast frequency (kHz)": 518,
   "NAVTEX CRS name": "Bjuröklubb",
   "NAVTEX CRS identifier": "H",
   "Country": "Sweden",
   "Latitude": "64° 28' N",
   "Longitude": "21° 36' E",
   "Broadcast range (NM)": "300",
   "Transmission times (All in UTC)": "0110, 0510, 0910, 1310, 1710, 2110",
   "Broadcast language": "English"
 },
 {
   "NAVAREA": "I",
   "Broadcast frequency (kHz)": 518,
   "NAVTEX CRS name": "Grimeton",
   "NAVTEX CRS identifier": "I",
   "Country": "Sweden",
   "Latitude": "57° 06' N",
   "Longitude": "12° 23' E",
   "Broadcast range (NM)": "300",
   "Transmission times (All in UTC)": "0120, 0520, 0920, 1320, 1720, 2120",
   "Broadcast language": "English"
 },
 {
   "NAVAREA": "I",
   "Broadcast frequency (kHz)": 518,
   "NAVTEX CRS name": "Gisövshammar",
   "NAVTEX CRS identifier": "J",
   "Country": "Sweden",
   "Latitude": "55° 29' N",
   "Longitude": "14° 19' E",
   "Broadcast range (NM)": "300",
   "Transmission times (All in UTC)": "0130, 0530, 0930, 1330, 1730, 2130",
   "Broadcast language": "English"
 },
 {
   "NAVAREA": "I",
   "Broadcast frequency (kHz)": 518,
   "NAVTEX CRS name": "Niton (N. France)",
   "NAVTEX CRS identifier": "K",
   "Country": "England",
   "Latitude": "50° 35' N",
   "Longitude": "01° 18' W",
   "Broadcast range (NM)": "270",
   "Transmission times (All in UTC)": "0140, 0540, 0940, 1340, 1740, 2140",
   "Broadcast language": "English"
 },
 {
   "NAVAREA": "I",
   "Broadcast frequency (kHz)": 518,
   "NAVTEX CRS name": "Rogaland",
   "NAVTEX CRS identifier": "L",
   "Country": "Norway",
   "Latitude": "58° 39' N",
   "Longitude": "05° 36' E",
   "Broadcast range (NM)": "450",
   "Transmission times (All in UTC)": "0150, 0550, 0950, 1350, 1750, 2150",
   "Broadcast language": "English"
 },
 {
   "NAVAREA": "I",
   "Broadcast frequency (kHz)": 518,
   "NAVTEX CRS name": "Oostende (Thames)",
   "NAVTEX CRS identifier": "M",
   "Country": "Belgium",
   "Latitude": "51° 11' N",
   "Longitude": "02° 48' E",
   "Broadcast range (NM)": "150",
   "Transmission times (All in UTC)": "0200, 0600, 1000, 1400, 1800, 2200",
   "Broadcast language": "English"
 },
 {
   "NAVAREA": "I",
   "Broadcast frequency (kHz)": 518,
   "NAVTEX CRS name": "Ørlandet",
   "NAVTEX CRS identifier": "N",
   "Country": "Norway",
   "Latitude": "63° 40' N",
   "Longitude": "09° 33' E",
   "Broadcast range (NM)": "450",
   "Transmission times (All in UTC)": "0210, 0610, 1010, 1410, 1810, 2210",
   "Broadcast language": "English"
 },
 {
   "NAVAREA": "I",
   "Broadcast frequency (kHz)": 518,
   "NAVTEX CRS name": "Portpatrick",
   "NAVTEX CRS identifier": "O",
   "Country": "Scotland",
   "Latitude": "54° 51' N",
   "Longitude": "05° 07' W",
   "Broadcast range (NM)": "270",
   "Transmission times (All in UTC)": "0220, 0620, 1020, 1420, 1820, 2220",
   "Broadcast language": "English"
 },
 {
   "NAVAREA": "I",
   "Broadcast frequency (kHz)": 518,
   "NAVTEX CRS name": "Netherlands Coast Guard",
   "NAVTEX CRS identifier": "P",
   "Country": "Netherlands",
   "Latitude": "52° 06' N",
   "Longitude": "04° 15' E",
   "Broadcast range (NM)": "250",
   "Transmission times (All in UTC)": "0230, 0630, 1030, 1430, 1830, 2230",
   "Broadcast language": "English"
 },
 {
   "NAVAREA": "I",
   "Broadcast frequency (kHz)": 518,
   "NAVTEX CRS name": "Malin Head Coast Guard",
   "NAVTEX CRS identifier": "Q",
   "Country": "Ireland",
   "Latitude": "55° 22' N",
   "Longitude": "07° 21' W",
   "Broadcast range (NM)": "400",
   "Transmission times (All in UTC)": "0240, 0640, 1040, 1440, 1840, 2240",
   "Broadcast language": "English"
 },
 {
   "NAVAREA": "I",
   "Broadcast frequency (kHz)": 518,
   "NAVTEX CRS name": "Reykjavik",
   "NAVTEX CRS identifier": "R",
   "Country": "Iceland",
   "Latitude": "64° 05' N",
   "Longitude": "21° 51' W",
   "Broadcast range (NM)": "550",
   "Transmission times (All in UTC)": "0250, 0650, 1050, 1450, 1850, 2250",
   "Broadcast language": "English"
 },
 {
   "NAVAREA": "I",
   "Broadcast frequency (kHz)": 518,
   "NAVTEX CRS name": "Pinneberg",
   "NAVTEX CRS identifier": "S",
   "Country": "Germany",
   "Latitude": "53° 43' N",
   "Longitude": "09° 55' E",
   "Broadcast range (NM)": "250-400",
   "Transmission times (All in UTC)": "0300, 0700, 1100, 1500, 1900, 2300",
   "Broadcast language": "English"
 },
 {
   "NAVAREA": "I",
   "Broadcast frequency (kHz)": 518,
   "NAVTEX CRS name": "Oostende",
   "NAVTEX CRS identifier": "T",
   "Country": "Belgium",
   "Latitude": "51° 11' N",
   "Longitude": "02° 48' E",
   "Broadcast range (NM)": "110",
   "Transmission times (All in UTC)": "0310, 0710, 1110, 1510, 1910, 2310",
   "Broadcast language": "English"
 },
 {
   "NAVAREA": "I",
   "Broadcast frequency (kHz)": 518,
   "NAVTEX CRS name": "Tallinn",
   "NAVTEX CRS identifier": "U",
   "Country": "Estonia",
   "Latitude": "59° 30' N",
   "Longitude": "24° 30' E",
   "Broadcast range (NM)": "300",
   "Transmission times (All in UTC)": "0320, 0720, 1120, 1520, 1920, 2320",
   "Broadcast language": "English"
 },
 {
   "NAVAREA": "I",
   "Broadcast frequency (kHz)": 518,
   "NAVTEX CRS name": "Vardø",
   "NAVTEX CRS identifier": "V",
   "Country": "Norway",
   "Latitude": "70° 22' N",
   "Longitude": "31° 06' E",
   "Broadcast range (NM)": "450",
   "Transmission times (All in UTC)": "0330, 0730, 1130, 1530, 1930, 2330",
   "Broadcast language": "English"
 },
 {
   "NAVAREA": "I",
   "Broadcast frequency (kHz)": 518,
   "NAVTEX CRS name": "Valentia Coast Guard",
   "NAVTEX CRS identifier": "W",
   "Country": "Ireland",
   "Latitude": "51° 27' N",
   "Longitude": "09° 49' W",
   "Broadcast range (NM)": "400",
   "Transmission times (All in UTC)": "0340, 0740, 1140, 1540, 1940, 2340",
   "Broadcast language": "English"
 },
 {
   "NAVAREA": "I",
   "Broadcast frequency (kHz)": 518,
   "NAVTEX CRS name": "Reykjavik",
   "NAVTEX CRS identifier": "X",
   "Country": "Iceland",
   "Latitude": "64° 05' N",
   "Longitude": "21° 51' W",
   "Broadcast range (NM)": "250",
   "Transmission times (All in UTC)": "0350, 0750, 1150, 1550, 1950, 2350",
   "Broadcast language": "English"
 },
 {
   "NAVAREA": "I",
   "Broadcast frequency (kHz)": 490,
   "NAVTEX CRS name": "Portpatrick",
   "NAVTEX CRS identifier": "C",
   "Country": "Scotland",
   "Latitude": "54° 51' N",
   "Longitude": "05° 07' W",
   "Broadcast range (NM)": "270",
   "Transmission times (All in UTC)": "0820, 2020",
   "Broadcast language": "English"
 },
 {
   "NAVAREA": "I",
   "Broadcast frequency (kHz)": 490,
   "NAVTEX CRS name": "Niton",
   "NAVTEX CRS identifier": "I",
   "Country": "England",
   "Latitude": "50° 35' N",
   "Longitude": "01° 18' W",
   "Broadcast range (NM)": "270",
   "Transmission times (All in UTC)": "0120, 0520, 0920, 1320, 1720, 2120",
   "Broadcast language": "English"
 },
 {
   "NAVAREA": "I",
   "Broadcast frequency (kHz)": 490,
   "NAVTEX CRS name": "Pinneberg",
   "NAVTEX CRS identifier": "L",
   "Country": "Germany",
   "Latitude": "53° 43' N",
   "Longitude": "09° 55' E",
   "Broadcast range (NM)": "250-400",
   "Transmission times (All in UTC)": "0150, 0550, 0950, 1350, 1750, 2150",
   "Broadcast language": "German"
 },
 {
   "NAVAREA": "I",
   "Broadcast frequency (kHz)": 490,
   "NAVTEX CRS name": "Reykjavík",
   "NAVTEX CRS identifier": "R",
   "Country": "Iceland",
   "Latitude": "64° 05' N",
   "Longitude": "21° 51' W",
   "Broadcast range (NM)": "550",
   "Transmission times (All in UTC)": "0320, 0720, 1120, 1520, 1920, 2320",
   "Broadcast language": "Icelandic"
 },
 {
   "NAVAREA": "I",
   "Broadcast frequency (kHz)": 490,
   "NAVTEX CRS name": "Niton (N. France)",
   "NAVTEX CRS identifier": "T",
   "Country": "England",
   "Latitude": "50° 35' N",
   "Longitude": "01° 18' W",
   "Broadcast range (NM)": "270",
   "Transmission times (All in UTC)": "0310, 0710, 1110, 1510, 1910, 2310",
   "Broadcast language": "French"
 },
 {
   "NAVAREA": "I",
   "Broadcast frequency (kHz)": 490,
   "NAVTEX CRS name": "Cullercoats",
   "NAVTEX CRS identifier": "U",
   "Country": "England",
   "Latitude": "55° 04' N",
   "Longitude": "01° 28' W",
   "Broadcast range (NM)": "270",
   "Transmission times (All in UTC)": "0720, 1920",
   "Broadcast language": "English"
 },
 {
   "NAVAREA": "II",
   "Broadcast frequency (kHz)": 518,
   "NAVTEX CRS name": "CROSS Corsen",
   "NAVTEX CRS identifier": "A",
   "Country": "France",
   "Latitude": "48° 24' N",
   "Longitude": "05° 03' W",
   "Broadcast range (NM)": "300",
   "Transmission times (All in UTC)": "0000, 0400, 0800, 1200, 1600, 2000",
   "Broadcast language": "English"
 },
 {
   "NAVAREA": "II",
   "Broadcast frequency (kHz)": 518,
   "NAVTEX CRS name": "Coruna",
   "NAVTEX CRS identifier": "D",
   "Country": "Spain",
   "Latitude": "43° 21' N",
   "Longitude": "08° 27' W",
   "Broadcast range (NM)": "400",
   "Transmission times (All in UTC)": "0030, 0430, 0830, 1230, 1630, 2030",
   "Broadcast language": "English"
 },
 {
   "NAVAREA": "II",
   "Broadcast frequency (kHz)": 518,
   "NAVTEX CRS name": "Horta",
   "NAVTEX CRS identifier": "F",
   "Country": "Azores",
   "Latitude": "38° 32' N",
   "Longitude": "28° 38' W",
   "Broadcast range (NM)": "640",
   "Transmission times (All in UTC)": "0050, 0450, 0850, 1250, 1650, 2050",
   "Broadcast language": "English"
 },
 {
   "NAVAREA": "II",
   "Broadcast frequency (kHz)": 518,
   "NAVTEX CRS name": "Tarifa",
   "NAVTEX CRS identifier": "G",
   "Country": "Spain",
   "Latitude": "36° 01' N",
   "Longitude": "05° 35' W",
   "Broadcast range (NM)": "400",
   "Transmission times (All in UTC)": "0100, 0500, 0900, 1300, 1700, 2100",
   "Broadcast language": "English"
 },
 {
   "NAVAREA": "II",
   "Broadcast frequency (kHz)": 518,
   "NAVTEX CRS name": "Las Palmas",
   "NAVTEX CRS identifier": "I",
   "Country": "Spain",
   "Latitude": "28° 25' N",
   "Longitude": "16° 23' W",
   "Broadcast range (NM)": "400",
   "Transmission times (All in UTC)": "0120, 0520, 0920, 1320, 1720, 2120",
   "Broadcast language": "English"
 },
 {
   "NAVAREA": "II",
   "Broadcast frequency (kHz)": 518,
   "NAVTEX CRS name": "Monsanto",
   "NAVTEX CRS identifier": "R",
   "Country": "Portugal",
   "Latitude": "38° 44' N",
   "Longitude": "09° 11' W",
   "Broadcast range (NM)": "530",
   "Transmission times (All in UTC)": "0250, 0650, 1050, 1450, 1850, 2250",
   "Broadcast language": "English"
 },
 {
   "NAVAREA": "II",
   "Broadcast frequency (kHz)": 518,
   "NAVTEX CRS name": "Ribeira de Vinha",
   "NAVTEX CRS identifier": "U",
   "Country": "Cape Verde",
   "Latitude": "16° 51' N",
   "Longitude": "25° 00' W",
   "Broadcast range (NM)": "250",
   "Transmission times (All in UTC)": "0320, 0720, 1120, 1520, 1920, 2320",
   "Broadcast language": "English"
 },
 {
   "NAVAREA": "II",
   "Broadcast frequency (kHz)": 490,
   "NAVTEX CRS name": "Las Palmas",
   "NAVTEX CRS identifier": "A",
   "Country": "Spain",
   "Latitude": "28° 25' N",
   "Longitude": "16° 23' W",
   "Broadcast range (NM)": "400",
   "Transmission times (All in UTC)": "0000, 0400, 0800, 1200, 1600, 2000",
   "Broadcast language": "Spanish"
 },
 {
   "NAVAREA": "II",
   "Broadcast frequency (kHz)": 490,
   "NAVTEX CRS name": "CROSS Corsen",
   "NAVTEX CRS identifier": "E",
   "Country": "France",
   "Latitude": "48° 24' N",
   "Longitude": "05° 03' W",
   "Broadcast range (NM)": "300",
   "Transmission times (All in UTC)": "0040, 0440, 0840, 1240, 1640, 2040",
   "Broadcast language": "French"
 },
 {
   "NAVAREA": "II",
   "Broadcast frequency (kHz)": 490,
   "NAVTEX CRS name": "Monsanto",
   "NAVTEX CRS identifier": "G",
   "Country": "Portugal",
   "Latitude": "38° 44' N",
   "Longitude": "09° 11' W",
   "Broadcast range (NM)": "530",
   "Transmission times (All in UTC)": "0100, 0500, 0900, 1300, 1700, 2100",
   "Broadcast language": "Portuguese"
 },
 {
   "NAVAREA": "II",
   "Broadcast frequency (kHz)": 490,
   "NAVTEX CRS name": "Horta",
   "NAVTEX CRS identifier": "J",
   "Country": "Azores",
   "Latitude": "38° 32' N",
   "Longitude": "28° 38' W",
   "Broadcast range (NM)": "640",
   "Transmission times (All in UTC)": "0130, 0530, 0930, 1330, 1730, 2130",
   "Broadcast language": "Portuguese"
 },
 {
   "NAVAREA": "II",
   "Broadcast frequency (kHz)": 490,
   "NAVTEX CRS name": "Ribeira de Vinha",
   "NAVTEX CRS identifier": "P",
   "Country": "Cape Verde",
   "Latitude": "16° 51' N",
   "Longitude": "25° 00' W",
   "Broadcast range (NM)": "250",
   "Transmission times (All in UTC)": "0230, 0630, 1030, 1430, 1830, 2230",
   "Broadcast language": "Portuguese"
 },
 {
   "NAVAREA": "II",
   "Broadcast frequency (kHz)": 490,
   "NAVTEX CRS name": "Tarifa",
   "NAVTEX CRS identifier": "T",
   "Country": "Spain",
   "Latitude": "36° 01' N",
   "Longitude": "05° 35' W",
   "Broadcast range (NM)": "400",
   "Transmission times (All in UTC)": "0310, 0710, 1110, 1510, 1910, 2310",
   "Broadcast language": "Spanish"
 },
 {
   "NAVAREA": "II",
   "Broadcast frequency (kHz)": 490,
   "NAVTEX CRS name": "Coruna",
   "NAVTEX CRS identifier": "W",
   "Country": "Spain",
   "Latitude": "43° 21' N",
   "Longitude": "08° 27' W",
   "Broadcast range (NM)": "400",
   "Transmission times (All in UTC)": "0340, 0740, 1140, 1540, 1940, 2340",
   "Broadcast language": "Spanish"
 },
 {
   "NAVAREA": "III",
   "Broadcast frequency (kHz)": 518,
   "NAVTEX CRS name": "Novorosiysk",
   "NAVTEX CRS identifier": "A",
   "Country": "Russia",
   "Latitude": "44° 43' N",
   "Longitude": "37° 47' E",
   "Broadcast range (NM)": "300",
   "Transmission times (All in UTC)": "0300, 0700, 1100, 1500, 1900, 2300",
   "Broadcast language": "English"
 },
 {
   "NAVAREA": "III",
   "Broadcast frequency (kHz)": 518,
   "NAVTEX CRS name": "Alger",
   "NAVTEX CRS identifier": "B",
   "Country": "Algeria",
   "Latitude": "36° 40' N",
   "Longitude": "03° 18' E",
   "Broadcast range (NM)": "500",
   "Transmission times (All in UTC)": "0010, 0410, 0810, 1210, 1610, 2010",
   "Broadcast language": "English"
 },
 {
   "NAVAREA": "III",
   "Broadcast frequency (kHz)": 518,
   "NAVTEX CRS name": "Kerch",
   "NAVTEX CRS identifier": "B",
   "Country": "Ukraine",
   "Latitude": "45° 23' N",
   "Longitude": "36° 28' E",
   "Broadcast range (NM)": "120",
   "Transmission times (All in UTC)": "0100, 0500, 0900, 1300, 1700, 2100",
   "Broadcast language": "English"
 },
 {
   "NAVAREA": "III",
   "Broadcast frequency (kHz)": 518,
   "NAVTEX CRS name": "Odesa",
   "NAVTEX CRS identifier": "C",
   "Country": "Ukraine",
   "Latitude": "46° 29' N",
   "Longitude": "30° 44' E",
   "Broadcast range (NM)": "280",
   "Transmission times (All in UTC)": "0020, 0420, 0820, 1220, 1620, 2020",
   "Broadcast language": "English"
 },
 {
   "NAVAREA": "III",
   "Broadcast frequency (kHz)": 518,
   "NAVTEX CRS name": "Istanbul",
   "NAVTEX CRS identifier": "D",
   "Country": "Turkey",
   "Latitude": "41° 04' N",
   "Longitude": "28° 57' E",
   "Broadcast range (NM)": "300",
   "Transmission times (All in UTC)": "0030, 0430, 0830, 1230, 1630, 2030",
   "Broadcast language": "English"
 },
 {
   "NAVAREA": "III",
   "Broadcast frequency (kHz)": 518,
   "NAVTEX CRS name": "Samsun",
   "NAVTEX CRS identifier": "E",
   "Country": "Turkey",
   "Latitude": "41° 17' N",
   "Longitude": "36° 20' E",
   "Broadcast range (NM)": "300",
   "Transmission times (All in UTC)": "0040, 0440, 0840, 1240, 1640, 2040",
   "Broadcast language": "English"
 },
 {
   "NAVAREA": "III",
   "Broadcast frequency (kHz)": 518,
   "NAVTEX CRS name": "Antalya",
   "NAVTEX CRS identifier": "F",
   "Country": "Turkey",
   "Latitude": "36° 53' N",
   "Longitude": "30° 42' E",
   "Broadcast range (NM)": "300",
   "Transmission times (All in UTC)": "0050, 0450, 0850, 1250, 1650, 2050",
   "Broadcast language": "English"
 },
 {
   "NAVAREA": "III",
   "Broadcast frequency (kHz)": 518,
   "NAVTEX CRS name": "Irákleio",
   "NAVTEX CRS identifier": "H",
   "Country": "Greece",
   "Latitude": "35° 20' N",
   "Longitude": "25° 07' E",
   "Broadcast range (NM)": "280",
   "Transmission times (All in UTC)": "0110, 0510, 0910, 1310, 1710, 2110",
   "Broadcast language": "English Greek"
 },
 {
   "NAVAREA": "III",
   "Broadcast frequency (kHz)": 518,
   "NAVTEX CRS name": "Izmir",
   "NAVTEX CRS identifier": "I",
   "Country": "Turkey",
   "Latitude": "38° 21' N",
   "Longitude": "26° 35' E",
   "Broadcast range (NM)": "300",
   "Transmission times (All in UTC)": "0120, 0520, 0920, 1320, 1720, 2120",
   "Broadcast language": "English"
 },
 {
   "NAVAREA": "III",
   "Broadcast frequency (kHz)": 518,
   "NAVTEX CRS name": "Varna",
   "NAVTEX CRS identifier": "J",
   "Country": "Bulgaria",
   "Latitude": "43° 04' N",
   "Longitude": "27° 46' E",
   "Broadcast range (NM)": "350",
   "Transmission times (All in UTC)": "0130, 0530, 0930, 1330, 1730, 2130",
   "Broadcast language": "English"
 },
 {
   "NAVAREA": "III",
   "Broadcast frequency (kHz)": 518,
   "NAVTEX CRS name": "Kerkyra",
   "NAVTEX CRS identifier": "K",
   "Country": "Greece",
   "Latitude": "39° 45' N",
   "Longitude": "19° 52' E",
   "Broadcast range (NM)": "280",
   "Transmission times (All in UTC)": "0140, 0540, 0940, 1340, 1740, 2140",
   "Broadcast language": "English Greek"
 },
 {
   "NAVAREA": "III",
   "Broadcast frequency (kHz)": 518,
   "NAVTEX CRS name": "Limnos",
   "NAVTEX CRS identifier": "L",
   "Country": "Greece",
   "Latitude": "39° 52' N",
   "Longitude": "25° 04' E",
   "Broadcast range (NM)": "280",
   "Transmission times (All in UTC)": "0150, 0550, 0950, 1350, 1750, 2150",
   "Broadcast language": "English Greek"
 },
 {
   "NAVAREA": "III",
   "Broadcast frequency (kHz)": 518,
   "NAVTEX CRS name": "Cyprus",
   "NAVTEX CRS identifier": "M",
   "Country": "Cyprus",
   "Latitude": "35° 02' N",
   "Longitude": "33° 17' E",
   "Broadcast range (NM)": "220",
   "Transmission times (All in UTC)": "0200, 0600, 1000, 1400, 1800, 2200",
   "Broadcast language": "English"
 },
 {
   "NAVAREA": "III",
   "Broadcast frequency (kHz)": 518,
   "NAVTEX CRS name": "Alexandria",
   "NAVTEX CRS identifier": "N",
   "Country": "Egypt",
   "Latitude": "31° 12' N",
   "Longitude": "29° 52' E",
   "Broadcast range (NM)": "350",
   "Transmission times (All in UTC)": "0210, 0610, 1010, 1410, 1810, 2210",
   "Broadcast language": "English"
 },
 {
   "NAVAREA": "III",
   "Broadcast frequency (kHz)": 518,
   "NAVTEX CRS name": "Malta",
   "NAVTEX CRS identifier": "O",
   "Country": "Malta",
   "Latitude": "35° 49' N",
   "Longitude": "14° 32' E",
   "Broadcast range (NM)": "400",
   "Transmission times (All in UTC)": "0220, 0620, 1020, 1420, 1820, 2220",
   "Broadcast language": "English"
 },
 {
   "NAVAREA": "III",
   "Broadcast frequency (kHz)": 518,
   "NAVTEX CRS name": "Haifa",
   "NAVTEX CRS identifier": "P",
   "Country": "Israel",
   "Latitude": "32° 49' N",
   "Longitude": "35° 00' E",
   "Broadcast range (NM)": "200",
   "Transmission times (All in UTC)": "0020, 0420, 0820, 1220, 1620, 2020",
   "Broadcast language": "English"
 },
 {
   "NAVAREA": "III",
   "Broadcast frequency (kHz)": 518,
   "NAVTEX CRS name": "Split",
   "NAVTEX CRS identifier": "Q",
   "Country": "Croatia",
   "Latitude": "43° 30' N",
   "Longitude": "16° 29' E",
   "Broadcast range (NM)": "150",
   "Transmission times (All in UTC)": "0240, 0640, 1040, 1440, 1840, 2240",
   "Broadcast language": "English"
 },
 {
   "NAVAREA": "III",
   "Broadcast frequency (kHz)": 518,
   "NAVTEX CRS name": "Roma",
   "NAVTEX CRS identifier": "R",
   "Country": "Italy",
   "Latitude": "41° 48' N",
   "Longitude": "12° 31' E",
   "Broadcast range (NM)": "320",
   "Transmission times (All in UTC)": "0250, 0650, 1050, 1450, 1850, 2250",
   "Broadcast language": "English Italian"
 },
 {
   "NAVAREA": "III",
   "Broadcast frequency (kHz)": 518,
   "NAVTEX CRS name": "Cagliari",
   "NAVTEX CRS identifier": "T",
   "Country": "Sardinia",
   "Latitude": "39° 14' N",
   "Longitude": "09° 14' E",
   "Broadcast range (NM)": "320",
   "Transmission times (All in UTC)": "0310, 0710, 1110, 1510, 1910, 2310",
   "Broadcast language": "English Italian"
 },
 {
   "NAVAREA": "III",
   "Broadcast frequency (kHz)": 518,
   "NAVTEX CRS name": "Trieste",
   "NAVTEX CRS identifier": "U",
   "Country": "Italy",
   "Latitude": "45° 41' N",
   "Longitude": "13° 46' E",
   "Broadcast range (NM)": "320",
   "Transmission times (All in UTC)": "0320, 0720, 1120, 1520, 1920, 2320",
   "Broadcast language": "English Italian"
 },
 {
   "NAVAREA": "III",
   "Broadcast frequency (kHz)": 518,
   "NAVTEX CRS name": "Augusta",
   "NAVTEX CRS identifier": "V",
   "Country": "Sicily",
   "Latitude": "37° 14' N",
   "Longitude": "15° 14' E",
   "Broadcast range (NM)": "320",
   "Transmission times (All in UTC)": "0330, 0730, 1130, 1530, 1930, 2330",
   "Broadcast language": "English Italian"
 },
 {
   "NAVAREA": "III",
   "Broadcast frequency (kHz)": 518,
   "NAVTEX CRS name": "CROSS La Garde",
   "NAVTEX CRS identifier": "W",
   "Country": "France",
   "Latitude": "43° 06' N",
   "Longitude": "05° 59' E",
   "Broadcast range (NM)": "250",
   "Transmission times (All in UTC)": "0340, 0740, 1140, 1540, 1940, 2340",
   "Broadcast language": "English"
 },
 {
   "NAVAREA": "III",
   "Broadcast frequency (kHz)": 518,
   "NAVTEX CRS name": "Valencia",
   "NAVTEX CRS identifier": "X",
   "Country": "Spain",
   "Latitude": "38° 43' N",
   "Longitude": "00° 09' W",
   "Broadcast range (NM)": "250",
   "Transmission times (All in UTC)": "0350, 0750, 1150, 1550, 1950, 2350",
   "Broadcast language": "English"
 },
 {
   "NAVAREA": "III",
   "Broadcast frequency (kHz)": 490,
   "NAVTEX CRS name": "Samsun",
   "NAVTEX CRS identifier": "A",
   "Country": "Turkey",
   "Latitude": "41° 17' N",
   "Longitude": "36° 20' E",
   "Broadcast range (NM)": "300",
   "Transmission times (All in UTC)": "0000, 0400, 0800, 1200, 1600, 2000",
   "Broadcast language": "Turkish"
 },
 {
   "NAVAREA": "III",
   "Broadcast frequency (kHz)": 490,
   "NAVTEX CRS name": "Istanbul",
   "NAVTEX CRS identifier": "B",
   "Country": "Turkey",
   "Latitude": "41° 04' N",
   "Longitude": "28° 57' E",
   "Broadcast range (NM)": "300",
   "Transmission times (All in UTC)": "0010, 0410, 0810, 1210, 1610, 2010",
   "Broadcast language": "Turkish"
 },
 {
   "NAVAREA": "III",
   "Broadcast frequency (kHz)": 490,
   "NAVTEX CRS name": "Izmir",
   "NAVTEX CRS identifier": "C",
   "Country": "Turkey",
   "Latitude": "38° 21' N",
   "Longitude": "26° 35' E",
   "Broadcast range (NM)": "300",
   "Transmission times (All in UTC)": "0020, 0420, 0820, 1220, 1620, 2020",
   "Broadcast language": "Turkish"
 },
 {
   "NAVAREA": "III",
   "Broadcast frequency (kHz)": 490,
   "NAVTEX CRS name": "Antalya",
   "NAVTEX CRS identifier": "D",
   "Country": "Turkey",
   "Latitude": "36° 53' N",
   "Longitude": "30° 42' E",
   "Broadcast range (NM)": "300",
   "Transmission times (All in UTC)": "0030, 0430, 0830, 1230, 1630, 2030",
   "Broadcast language": "Turkish"
 },
 {
   "NAVAREA": "III",
   "Broadcast frequency (kHz)": 490,
   "NAVTEX CRS name": "Constanta",
   "NAVTEX CRS identifier": "L",
   "Country": "Romania",
   "Latitude": "44° 12' N",
   "Longitude": "28° 40' E",
   "Broadcast range (NM)": "250",
   "Transmission times (All in UTC)": "0150, 0550, 0950, 1350, 1750, 2150",
   "Broadcast language": "Romanian"
 },
 {
   "NAVAREA": "III",
   "Broadcast frequency (kHz)": 490,
   "NAVTEX CRS name": "Valencia",
   "NAVTEX CRS identifier": "M",
   "Country": "Spain",
   "Latitude": "39° 27' N",
   "Longitude": "00° 20' W",
   "Broadcast range (NM)": "300",
   "Transmission times (All in UTC)": "0200, 0600, 1000, 1400, 1800, 2200",
   "Broadcast language": "Spanish"
 },
 {
   "NAVAREA": "III",
   "Broadcast frequency (kHz)": 490,
   "NAVTEX CRS name": "CROSS La Garde",
   "NAVTEX CRS identifier": "S",
   "Country": "France",
   "Latitude": "43° 06' N",
   "Longitude": "05° 59' E",
   "Broadcast range (NM)": "250",
   "Transmission times (All in UTC)": "0300, 0700, 1100, 1500, 1900, 2300",
   "Broadcast language": "French"
 },
 {
   "NAVAREA": "III",
   "Broadcast frequency (kHz)": 490,
   "NAVTEX CRS name": "Alger",
   "NAVTEX CRS identifier": "V",
   "Country": "Algeria",
   "Latitude": "36° 40' N",
   "Longitude": "03° 18' E",
   "Broadcast range (NM)": "500",
   "Transmission times (All in UTC)": "0330, 0730, 1130, 1530, 1930, 2330",
   "Broadcast language": "French"
 },
 {
   "NAVAREA": "III",
   "Broadcast frequency (kHz)": 4209.5,
   "NAVTEX CRS name": "Istanbul",
   "NAVTEX CRS identifier": "M",
   "Country": "Turkey",
   "Latitude": "41° 04' N",
   "Longitude": "28° 57' E",
   "Broadcast range (NM)": "300",
   "Transmission times (All in UTC)": "0200, 0600, 1000, 1400, 1800, 2200",
   "Broadcast language": "Turkish"
 },
 {
   "NAVAREA": "IV",
   "Broadcast frequency (kHz)": 518,
   "NAVTEX CRS name": "Miami",
   "NAVTEX CRS identifier": "A",
   "Country": "USA",
   "Latitude": "25° 30' N",
   "Longitude": "80° 23' W",
   "Broadcast range (NM)": "240",
   "Transmission times (All in UTC)": "0000, 0400, 0800, 1200, 1600, 2000",
   "Broadcast language": "English"
 },
 {
   "NAVAREA": "IV",
   "Broadcast frequency (kHz)": 518,
   "NAVTEX CRS name": "Bermuda Harbour",
   "NAVTEX CRS identifier": "B",
   "Country": "Bermuda",
   "Latitude": "32° 23' N",
   "Longitude": "64° 41' W",
   "Broadcast range (NM)": "280",
   "Transmission times (All in UTC)": "0010, 0410, 0810, 1210, 1610, 2010",
   "Broadcast language": "English"
 },
 {
   "NAVAREA": "IV",
   "Broadcast frequency (kHz)": 518,
   "NAVTEX CRS name": "Riviere-au-Renard",
   "NAVTEX CRS identifier": "C",
   "Country": "Canada",
   "Latitude": "50° 11' N",
   "Longitude": "66° 07' W",
   "Broadcast range (NM)": "300",
   "Transmission times (All in UTC)": "0020, 0420, 0820, 1220, 1620, 2020",
   "Broadcast language": "English"
 },
 {
   "NAVAREA": "IV",
   "Broadcast frequency (kHz)": 518,
   "NAVTEX CRS name": "Savannah",
   "NAVTEX CRS identifier": "E",
   "Country": "USA",
   "Latitude": "32° 08' N",
   "Longitude": "81° 42' W",
   "Broadcast range (NM)": "200",
   "Transmission times (All in UTC)": "0040, 0440, 0840, 1240, 1640, 2040",
   "Broadcast language": "English"
 },
 {
   "NAVAREA": "IV",
   "Broadcast frequency (kHz)": 518,
   "NAVTEX CRS name": "Boston",
   "NAVTEX CRS identifier": "F",
   "Country": "USA",
   "Latitude": "41° 43' N",
   "Longitude": "70° 31' W",
   "Broadcast range (NM)": "200",
   "Transmission times (All in UTC)": "0045, 0445, 0845, 1245, 1645, 2045",
   "Broadcast language": "English"
 },
 {
   "NAVAREA": "IV",
   "Broadcast frequency (kHz)": 518,
   "NAVTEX CRS name": "New Orleans",
   "NAVTEX CRS identifier": "G",
   "Country": "USA",
   "Latitude": "29° 53' N",
   "Longitude": "89° 55' W",
   "Broadcast range (NM)": "200",
   "Transmission times (All in UTC)": "0300, 0700, 1100, 1500, 1900, 2300",
   "Broadcast language": "English"
 },
 {
   "NAVAREA": "IV",
   "Broadcast frequency (kHz)": 518,
   "NAVTEX CRS name": "Prescott",
   "NAVTEX CRS identifier": "H",
   "Country": "Canada",
   "Latitude": "45° 42' N",
   "Longitude": "125° 32' W",
   "Broadcast range (NM)": "300",
   "Transmission times (All in UTC)": "0110, 0510, 0910, 1310, 1710, 2110",
   "Broadcast language": "English"
 },
 {
   "NAVAREA": "IV",
   "Broadcast frequency (kHz)": 518,
   "NAVTEX CRS name": "Curacao",
   "NAVTEX CRS identifier": "H",
   "Country": "Netherland Antilles",
   "Latitude": "12° 10' N",
   "Longitude": "68° 52' W",
   "Broadcast range (NM)": "250",
   "Transmission times (All in UTC)": "0110, 0510, 0910, 1310, 1710, 2110",
   "Broadcast language": "English"
 },
 {
   "NAVAREA": "IV",
   "Broadcast frequency (kHz)": 518,
   "NAVTEX CRS name": "Portsmouth",
   "NAVTEX CRS identifier": "N",
   "Country": "USA",
   "Latitude": "36° 44' N",
   "Longitude": "76° 01' W",
   "Broadcast range (NM)": "280",
   "Transmission times (All in UTC)": "0130, 0530, 0930, 1330, 1730, 2130",
   "Broadcast language": "English"
 },
 {
   "NAVAREA": "IV",
   "Broadcast frequency (kHz)": 518,
   "NAVTEX CRS name": "St.Johns",
   "NAVTEX CRS identifier": "O",
   "Country": "Canada",
   "Latitude": "47° 37' N",
   "Longitude": "52° 40' W",
   "Broadcast range (NM)": "300",
   "Transmission times (All in UTC)": "0220, 0620, 1020, 1420, 1820, 2220",
   "Broadcast language": "English"
 },
 {
   "NAVAREA": "IV",
   "Broadcast frequency (kHz)": 518,
   "NAVTEX CRS name": "Thunder Bay",
   "NAVTEX CRS identifier": "P",
   "Country": "Canada",
   "Latitude": "48° 26' N",
   "Longitude": "89° 13' W",
   "Broadcast range (NM)": "300",
   "Transmission times (All in UTC)": "0230, 0630, 1030, 1430, 1830, 2230",
   "Broadcast language": "English"
 },
 {
   "NAVAREA": "IV",
   "Broadcast frequency (kHz)": 518,
   "NAVTEX CRS name": "Sydney",
   "NAVTEX CRS identifier": "Q",
   "Country": "Canada",
   "Latitude": "46° 11' N",
   "Longitude": "59° 54' W",
   "Broadcast range (NM)": "300",
   "Transmission times (All in UTC)": "0240, 0640, 1040, 1440, 1840, 2240",
   "Broadcast language": "English"
 },
 {
   "NAVAREA": "IV",
   "Broadcast frequency (kHz)": 518,
   "NAVTEX CRS name": "Isabella – San Juan",
   "NAVTEX CRS identifier": "R",
   "Country": "Puerto Rico",
   "Latitude": "18° 28' N",
   "Longitude": "67° 04' W",
   "Broadcast range (NM)": "200",
   "Transmission times (All in UTC)": "0200, 0600, 1000, 1400, 1800, 2200",
   "Broadcast language": "English"
 },
 {
   "NAVAREA": "IV",
   "Broadcast frequency (kHz)": 518,
   "NAVTEX CRS name": "Iqaluit",
   "NAVTEX CRS identifier": "T",
   "Country": "Canada",
   "Latitude": "63° 44' N",
   "Longitude": "68° 33' W",
   "Broadcast range (NM)": "150",
   "Transmission times (All in UTC)": "0310, 0710, 1110, 1510, 1910, 2310",
   "Broadcast language": "English"
 },
 {
   "NAVAREA": "IV",
   "Broadcast frequency (kHz)": 518,
   "NAVTEX CRS name": "Fundy",
   "NAVTEX CRS identifier": "U",
   "Country": "Canada",
   "Latitude": "45° 14' N",
   "Longitude": "65° 59' W",
   "Broadcast range (NM)": "300",
   "Transmission times (All in UTC)": "0320, 0720, 1120, 1520, 1920, 2320",
   "Broadcast language": "English"
 },
 {
   "NAVAREA": "IV",
   "Broadcast frequency (kHz)": 518,
   "NAVTEX CRS name": "Nuuk (Kook Island)",
   "NAVTEX CRS identifier": "W",
   "Country": "Greenland",
   "Latitude": "64° 04' N",
   "Longitude": "52° 02' W",
   "Broadcast range (NM)": "400",
   "Transmission times (All in UTC)": "0340, 0740, 1140, 1540, 1940, 2340",
   "Broadcast language": "English"
 },
 {
   "NAVAREA": "IV",
   "Broadcast frequency (kHz)": 518,
   "NAVTEX CRS name": "Labrador",
   "NAVTEX CRS identifier": "X",
   "Country": "Canada",
   "Latitude": "53° 18' N",
   "Longitude": "60° 33' W",
   "Broadcast range (NM)": "300",
   "Transmission times (All in UTC)": "0350, 0750, 1150, 1550, 1950, 2350",
   "Broadcast language": "English"
 },
 {
   "NAVAREA": "IV",
   "Broadcast frequency (kHz)": 490,
   "NAVTEX CRS name": "Riviere-au-Renard",
   "NAVTEX CRS identifier": "D",
   "Country": "Canada",
   "Latitude": "50° 11' N",
   "Longitude": "66° 07' W",
   "Broadcast range (NM)": "300",
   "Transmission times (All in UTC)": "0035, 0435, 0835, 1235, 1635, 2035",
   "Broadcast language": "French"
 },
 {
   "NAVAREA": "IV",
   "Broadcast frequency (kHz)": 490,
   "NAVTEX CRS name": "Sydney",
   "NAVTEX CRS identifier": "J",
   "Country": "Canada",
   "Latitude": "46° 11' N",
   "Longitude": "59° 54' W",
   "Broadcast range (NM)": "300",
   "Transmission times (All in UTC)": "0255, 0655, 1055, 1455, 1855, 2255",
   "Broadcast language": "French"
 },
 {
   "NAVAREA": "IV",
   "Broadcast frequency (kHz)": 490,
   "NAVTEX CRS name": "Iqaluit",
   "NAVTEX CRS identifier": "S",
   "Country": "Canada",
   "Latitude": "63° 44' N",
   "Longitude": "68° 33' W",
   "Broadcast range (NM)": "150",
   "Transmission times (All in UTC)": "0300, 0700, 1100, 1500, 1900, 2300",
   "Broadcast language": "French"
 },
 {
   "NAVAREA": "IV",
   "Broadcast frequency (kHz)": 490,
   "NAVTEX CRS name": "Fundy",
   "NAVTEX CRS identifier": "V",
   "Country": "Canada",
   "Latitude": "43° 45' N",
   "Longitude": "66° 10' W",
   "Broadcast range (NM)": "300",
   "Transmission times (All in UTC)": "0335, 0735, 1135, 1535, 1935, 2335",
   "Broadcast language": "French"
 },
 {
   "NAVAREA": "VI",
   "Broadcast frequency (kHz)": 518,
   "NAVTEX CRS name": "La Paloma",
   "NAVTEX CRS identifier": "F",
   "Country": "Uruguay",
   "Latitude": "34° 40' S",
   "Longitude": "54° 09' W",
   "Broadcast range (NM)": "280",
   "Transmission times (All in UTC)": "0050, 0450, 0850, 1250, 1650, 2050",
   "Broadcast language": "English"
 },
 {
   "NAVAREA": "VI",
   "Broadcast frequency (kHz)": 518,
   "NAVTEX CRS name": "Ushuaia",
   "NAVTEX CRS identifier": "M",
   "Country": "Argentina",
   "Latitude": "54° 48' S",
   "Longitude": "68° 18' W",
   "Broadcast range (NM)": "280",
   "Transmission times (All in UTC)": "0200, 0600, 1000, 1400, 1800, 2200",
   "Broadcast language": "English"
 },
 {
   "NAVAREA": "VI",
   "Broadcast frequency (kHz)": 518,
   "NAVTEX CRS name": "Río Gallegos",
   "NAVTEX CRS identifier": "N",
   "Country": "Argentina",
   "Latitude": "51° 37' S",
   "Longitude": "69° 03' W",
   "Broadcast range (NM)": "280",
   "Transmission times (All in UTC)": "0210, 0610, 1010, 1410, 1810, 2210",
   "Broadcast language": "English"
 },
 {
   "NAVAREA": "VI",
   "Broadcast frequency (kHz)": 518,
   "NAVTEX CRS name": "Comodoro Rivadavia",
   "NAVTEX CRS identifier": "O",
   "Country": "Argentina",
   "Latitude": "45° 51' S",
   "Longitude": "67° 25' W",
   "Broadcast range (NM)": "280",
   "Transmission times (All in UTC)": "0220, 0620, 1020, 1420, 1820, 2220",
   "Broadcast language": "English"
 },
 {
   "NAVAREA": "VI",
   "Broadcast frequency (kHz)": 518,
   "NAVTEX CRS name": "Bahia Blanca",
   "NAVTEX CRS identifier": "P",
   "Country": "Argentina",
   "Latitude": "38° 43' S",
   "Longitude": "62° 06' W",
   "Broadcast range (NM)": "280",
   "Transmission times (All in UTC)": "0230, 0630, 1030, 1430, 1830, 2230",
   "Broadcast language": "English"
 },
 {
   "NAVAREA": "VI",
   "Broadcast frequency (kHz)": 518,
   "NAVTEX CRS name": "Mar Del Plata",
   "NAVTEX CRS identifier": "Q",
   "Country": "Argentina",
   "Latitude": "38° 03' S",
   "Longitude": "57° 32' W",
   "Broadcast range (NM)": "280",
   "Transmission times (All in UTC)": "0240, 0640, 1040, 1440, 1840, 2240",
   "Broadcast language": "English"
 },
 {
   "NAVAREA": "VI",
   "Broadcast frequency (kHz)": 518,
   "NAVTEX CRS name": "Buenos Aires",
   "NAVTEX CRS identifier": "R",
   "Country": "Argentina",
   "Latitude": "34° 36' S",
   "Longitude": "58° 22' W",
   "Broadcast range (NM)": "560",
   "Transmission times (All in UTC)": "0250, 0650, 1050, 1450, 1850, 2250",
   "Broadcast language": "English"
 },
 {
   "NAVAREA": "VI",
   "Broadcast frequency (kHz)": 490,
   "NAVTEX CRS name": "La Paloma",
   "NAVTEX CRS identifier": "A",
   "Country": "Uruguay",
   "Latitude": "34° 40' S",
   "Longitude": "54° 09' W",
   "Broadcast range (NM)": "280",
   "Transmission times (All in UTC)": "0000, 0400, 0800, 1200, 1600, 2000",
   "Broadcast language": "Spanish"
 },
 {
   "NAVAREA": "VI",
   "Broadcast frequency (kHz)": 490,
   "NAVTEX CRS name": "Ushuaia",
   "NAVTEX CRS identifier": "A",
   "Country": "Argentina",
   "Latitude": "54° 48' S",
   "Longitude": "68° 18' W",
   "Broadcast range (NM)": "280",
   "Transmission times (All in UTC)": "0000, 0400, 0800, 1200, 1600, 2000",
   "Broadcast language": "Spanish"
 },
 {
   "NAVAREA": "VI",
   "Broadcast frequency (kHz)": 490,
   "NAVTEX CRS name": "Río Gallegos",
   "NAVTEX CRS identifier": "B",
   "Country": "Argentina",
   "Latitude": "51° 37' S",
   "Longitude": "69° 03' W",
   "Broadcast range (NM)": "280",
   "Transmission times (All in UTC)": "0010, 0410, 0810, 1210, 1610, 2010",
   "Broadcast language": "Spanish"
 },
 {
   "NAVAREA": "VI",
   "Broadcast frequency (kHz)": 490,
   "NAVTEX CRS name": "Comodoro Rivadavia",
   "NAVTEX CRS identifier": "C",
   "Country": "Argentina",
   "Latitude": "45° 51' S",
   "Longitude": "67° 25' W",
   "Broadcast range (NM)": "280",
   "Transmission times (All in UTC)": "0020, 0420, 0820, 1220, 1620, 2020",
   "Broadcast language": "Spanish"
 },
 {
   "NAVAREA": "VI",
   "Broadcast frequency (kHz)": 490,
   "NAVTEX CRS name": "Bahia Blanca",
   "NAVTEX CRS identifier": "D",
   "Country": "Argentina",
   "Latitude": "38° 43' S",
   "Longitude": "62° 06' W",
   "Broadcast range (NM)": "280",
   "Transmission times (All in UTC)": "0030, 0430, 0830, 1230, 1630, 2030",
   "Broadcast language": "Spanish"
 },
 {
   "NAVAREA": "VI",
   "Broadcast frequency (kHz)": 490,
   "NAVTEX CRS name": "Mar Del Plata",
   "NAVTEX CRS identifier": "E",
   "Country": "Argentina",
   "Latitude": "38° 03' S",
   "Longitude": "57° 32' W",
   "Broadcast range (NM)": "280",
   "Transmission times (All in UTC)": "0040, 0440, 0840, 1240, 1640, 2040",
   "Broadcast language": "Spanish"
 },
 {
   "NAVAREA": "VI",
   "Broadcast frequency (kHz)": 490,
   "NAVTEX CRS name": "Buenos Aires",
   "NAVTEX CRS identifier": "F",
   "Country": "Argentina",
   "Latitude": "34° 36' S",
   "Longitude": "58° 22' W",
   "Broadcast range (NM)": "560",
   "Transmission times (All in UTC)": "0050, 0450, 0850, 1250, 1650, 2050",
   "Broadcast language": "Spanish"
 },
 {
   "NAVAREA": "VII",
   "Broadcast frequency (kHz)": 518,
   "NAVTEX CRS name": "Walvis Bay",
   "NAVTEX CRS identifier": "B",
   "Country": "Namibia",
   "Latitude": "23° 03' S",
   "Longitude": "14° 37' E",
   "Broadcast range (NM)": "380",
   "Transmission times (All in UTC)": "0010, 0410, 0810, 1210, 1610, 2010",
   "Broadcast language": "English"
 },
 {
   "NAVAREA": "VII",
   "Broadcast frequency (kHz)": 518,
   "NAVTEX CRS name": "Cape Town",
   "NAVTEX CRS identifier": "C",
   "Country": "South Africa",
   "Latitude": "33° 41' S",
   "Longitude": "18° 43' E",
   "Broadcast range (NM)": "500",
   "Transmission times (All in UTC)": "0020, 0420, 0820, 1220, 1620, 2020",
   "Broadcast language": "English"
 },
 {
   "NAVAREA": "VII",
   "Broadcast frequency (kHz)": 518,
   "NAVTEX CRS name": "Port Elizabeth",
   "NAVTEX CRS identifier": "I",
   "Country": "South Africa",
   "Latitude": "33° 57' S",
   "Longitude": "25° 31' E",
   "Broadcast range (NM)": "500",
   "Transmission times (All in UTC)": "0120, 0520, 0920, 1320, 1720, 2120",
   "Broadcast language": "English"
 },
 {
   "NAVAREA": "VII",
   "Broadcast frequency (kHz)": 518,
   "NAVTEX CRS name": "Durban",
   "NAVTEX CRS identifier": "O",
   "Country": "South Africa",
   "Latitude": "29° 48' S",
   "Longitude": "30° 49' E",
   "Broadcast range (NM)": "250",
   "Transmission times (All in UTC)": "0220, 0620, 1020, 1420, 1820, 2220",
   "Broadcast language": "English"
 },
 {
   "NAVAREA": "VIII",
   "Broadcast frequency (kHz)": 518,
   "NAVTEX CRS name": "Mauritius Radio",
   "NAVTEX CRS identifier": "C",
   "Country": "Mauritius",
   "Latitude": "20° 10' S",
   "Longitude": "57° 28' E",
   "Broadcast range (NM)": "400",
   "Transmission times (All in UTC)": "0020, 0420, 0820, 1220, 1620, 2020",
   "Broadcast language": "English"
 },
 {
   "NAVAREA": "VIII",
   "Broadcast frequency (kHz)": 518,
   "NAVTEX CRS name": "Bombay",
   "NAVTEX CRS identifier": "G",
   "Country": "India",
   "Latitude": "19° 05' N",
   "Longitude": "72° 50' E",
   "Broadcast range (NM)": "250",
   "Transmission times (All in UTC)": "0100, 0500, 0900, 1300, 1700, 2100",
   "Broadcast language": "English"
 },
 {
   "NAVAREA": "VIII",
   "Broadcast frequency (kHz)": 518,
   "NAVTEX CRS name": "Madras",
   "NAVTEX CRS identifier": "P",
   "Country": "India",
   "Latitude": "13° 05' N",
   "Longitude": "80° 17' E",
   "Broadcast range (NM)": "250",
   "Transmission times (All in UTC)": "0230, 0630, 1030, 1430, 1830, 2230",
   "Broadcast language": "English"
 },
 {
   "NAVAREA": "IX",
   "Broadcast frequency (kHz)": 518,
   "NAVTEX CRS name": "Bushehr",
   "NAVTEX CRS identifier": "A",
   "Country": "Iran",
   "Latitude": "28° 58' N",
   "Longitude": "50° 50' E",
   "Broadcast range (NM)": "300",
   "Transmission times (All in UTC)": "0000, 0400, 0800, 1200, 1600, 2000",
   "Broadcast language": "English"
 },
 {
   "NAVAREA": "IX",
   "Broadcast frequency (kHz)": 518,
   "NAVTEX CRS name": "Hamala",
   "NAVTEX CRS identifier": "B",
   "Country": "Bahrain",
   "Latitude": "26° 13' N",
   "Longitude": "50° 39' E",
   "Broadcast range (NM)": "300",
   "Transmission times (All in UTC)": "0010, 0410, 0810, 1210, 1610, 2010",
   "Broadcast language": "English"
 },
 {
   "NAVAREA": "IX",
   "Broadcast frequency (kHz)": 518,
   "NAVTEX CRS name": "Bandar Abbas",
   "NAVTEX CRS identifier": "F",
   "Country": "Iran",
   "Latitude": "27° 08' N",
   "Longitude": "57° 04' E",
   "Broadcast range (NM)": "300",
   "Transmission times (All in UTC)": "0050, 0450, 0850, 1250, 1650, 2050",
   "Broadcast language": "English"
 },
 {
   "NAVAREA": "IX",
   "Broadcast frequency (kHz)": 518,
   "NAVTEX CRS name": "Dammam",
   "NAVTEX CRS identifier": "G",
   "Country": "Saudi Arabia",
   "Latitude": "26° 26' N",
   "Longitude": "50° 06' E",
   "Broadcast range (NM)": "390",
   "Transmission times (All in UTC)": "0100, 0500, 0900, 1300, 1700, 2100",
   "Broadcast language": "English"
 },
 {
   "NAVAREA": "IX",
   "Broadcast frequency (kHz)": 518,
   "NAVTEX CRS name": "Jeddah",
   "NAVTEX CRS identifier": "H",
   "Country": "Saudi Arabia",
   "Latitude": "21° 23' N",
   "Longitude": "39° 11' E",
   "Broadcast range (NM)": "390",
   "Transmission times (All in UTC)": "0110, 0510, 0910, 1310, 1710, 2110",
   "Broadcast language": "English"
 },
 {
   "NAVAREA": "IX",
   "Broadcast frequency (kHz)": 518,
   "NAVTEX CRS name": "Muscat",
   "NAVTEX CRS identifier": "M",
   "Country": "Oman",
   "Latitude": "23° 37' N",
   "Longitude": "58° 31' E",
   "Broadcast range (NM)": "270",
   "Transmission times (All in UTC)": "0200, 0600, 1000, 1400, 1800, 2200",
   "Broadcast language": "English"
 },
 {
   "NAVAREA": "IX",
   "Broadcast frequency (kHz)": 518,
   "NAVTEX CRS name": "Karachi",
   "NAVTEX CRS identifier": "P",
   "Country": "Pakistan",
   "Latitude": "24° 51' N",
   "Longitude": "67° 03' E",
   "Broadcast range (NM)": "400",
   "Transmission times (All in UTC)": "0230, 0630, 1030, 1430, 1830, 2230",
   "Broadcast language": "English"
 },
 {
   "NAVAREA": "IX",
   "Broadcast frequency (kHz)": 518,
   "NAVTEX CRS name": "El Qusheir",
   "NAVTEX CRS identifier": "V",
   "Country": "Egypt",
   "Latitude": "26° 06' N",
   "Longitude": "34° 17' E",
   "Broadcast range (NM)": "350",
   "Transmission times (All in UTC)": "0330, 0730, 1130, 1530, 1930, 2330",
   "Broadcast language": "English"
 },
 {
   "NAVAREA": "IX",
   "Broadcast frequency (kHz)": 518,
   "NAVTEX CRS name": "Serapeum (Ismailia)",
   "NAVTEX CRS identifier": "X",
   "Country": "Egypt",
   "Latitude": "30° 35' N",
   "Longitude": "32° 17' E",
   "Broadcast range (NM)": "400",
   "Transmission times (All in UTC)": "0350, 0750, 1150, 1550, 1950, 2350",
   "Broadcast language": "English"
 },
 {
   "NAVAREA": "XI",
   "Broadcast frequency (kHz)": 518,
   "NAVTEX CRS name": "Jayapura",
   "NAVTEX CRS identifier": "A",
   "Country": "Indonesia",
   "Latitude": "02° 31' S",
   "Longitude": "140° 43' E",
   "Broadcast range (NM)": "300",
   "Transmission times (All in UTC)": "0000, 0400, 0800, 1200, 1600, 2000",
   "Broadcast language": "English"
 },
 {
   "NAVAREA": "XI",
   "Broadcast frequency (kHz)": 518,
   "NAVTEX CRS name": "Amboina",
   "NAVTEX CRS identifier": "B",
   "Country": "Indonesia",
   "Latitude": "03° 42' S",
   "Longitude": "128° 12' E",
   "Broadcast range (NM)": "300",
   "Transmission times (All in UTC)": "0010, 0410, 0810, 1210, 1610, 2010",
   "Broadcast language": "English"
 },
 {
   "NAVAREA": "XI",
   "Broadcast frequency (kHz)": 518,
   "NAVTEX CRS name": "Singapore",
   "NAVTEX CRS identifier": "C",
   "Country": "Singapore",
   "Latitude": "01° 20' N",
   "Longitude": "103° 42' E",
   "Broadcast range (NM)": "400",
   "Transmission times (All in UTC)": "0020, 0420, 0820, 1220, 1620, 2020",
   "Broadcast language": "English"
 },
 {
   "NAVAREA": "XI",
   "Broadcast frequency (kHz)": 518,
   "NAVTEX CRS name": "Makassar",
   "NAVTEX CRS identifier": "D",
   "Country": "Indonesia",
   "Latitude": "05° 06' S",
   "Longitude": "119° 26' E",
   "Broadcast range (NM)": "300",
   "Transmission times (All in UTC)": "0030, 0430, 0830, 1230, 1630, 2030",
   "Broadcast language": "English"
 },
 {
   "NAVAREA": "XI",
   "Broadcast frequency (kHz)": 518,
   "NAVTEX CRS name": "Jakarta",
   "NAVTEX CRS identifier": "E",
   "Country": "Indonesia",
   "Latitude": "06° 07' S",
   "Longitude": "106° 52' E",
   "Broadcast range (NM)": "300",
   "Transmission times (All in UTC)": "0040, 0440, 0840, 1240, 1640, 2040",
   "Broadcast language": "English"
 },
 {
   "NAVAREA": "XI",
   "Broadcast frequency (kHz)": 518,
   "NAVTEX CRS name": "Bangkok (Nonthaburi)",
   "NAVTEX CRS identifier": "F",
   "Country": "Thailand",
   "Latitude": "13° 01' N",
   "Longitude": "100° 01' E",
   "Broadcast range (NM)": "200",
   "Transmission times (All in UTC)": "0050, 0450, 0850, 1200",
   "Broadcast language": "English"
 },
 {
   "NAVAREA": "XI",
   "Broadcast frequency (kHz)": 518,
   "NAVTEX CRS name": "Naha",
   "NAVTEX CRS identifier": "G",
   "Country": "Japan",
   "Latitude": "26° 09' N",
   "Longitude": "127° 46' E",
   "Broadcast range (NM)": "400",
   "Transmission times (All in UTC)": "0100, 0500, 0900, 1300, 1700, 2100",
   "Broadcast language": "English"
 },
 {
   "NAVAREA": "XI",
   "Broadcast frequency (kHz)": 518,
   "NAVTEX CRS name": "Moji",
   "NAVTEX CRS identifier": "H",
   "Country": "Japan",
   "Latitude": "33° 52' N",
   "Longitude": "130° 36' E",
   "Broadcast range (NM)": "400",
   "Transmission times (All in UTC)": "0110, 0510, 0910, 1310, 1710, 2110",
   "Broadcast language": "English"
 },
 {
   "NAVAREA": "XI",
   "Broadcast frequency (kHz)": 518,
   "NAVTEX CRS name": "Yokohama",
   "NAVTEX CRS identifier": "I",
   "Country": "Japan",
   "Latitude": "35° 22' N",
   "Longitude": "118° 43' E",
   "Broadcast range (NM)": "400",
   "Transmission times (All in UTC)": "0120, 0520, 0920, 1320, 1720, 2120",
   "Broadcast language": "English"
 },
 {
   "NAVAREA": "XI",
   "Broadcast frequency (kHz)": 518,
   "NAVTEX CRS name": "Otaru",
   "NAVTEX CRS identifier": "J",
   "Country": "Japan",
   "Latitude": "43° 12' N",
   "Longitude": "141° 00' E",
   "Broadcast range (NM)": "400",
   "Transmission times (All in UTC)": "0130, 0530, 0930, 1330, 1730, 2130",
   "Broadcast language": "English"
 },
 {
   "NAVAREA": "XI",
   "Broadcast frequency (kHz)": 518,
   "NAVTEX CRS name": "Da Nang",
   "NAVTEX CRS identifier": "K",
   "Country": "Vietnam",
   "Latitude": "16° 05' N",
   "Longitude": "108° 13' E",
   "Broadcast range (NM)": "400",
   "Transmission times (All in UTC)": "0140, 0540, 0940, 1340, 1740, 2140",
   "Broadcast language": "English"
 },
 {
   "NAVAREA": "XI",
   "Broadcast frequency (kHz)": 518,
   "NAVTEX CRS name": "Otaru",
   "NAVTEX CRS identifier": "K",
   "Country": "Japan",
   "Latitude": "42° 57' N",
   "Longitude": "144° 36' E",
   "Broadcast range (NM)": "400",
   "Transmission times (All in UTC)": "0140, 0540, 0940, 1340, 1740, 2140",
   "Broadcast language": "English"
 },
 {
   "NAVAREA": "XI",
   "Broadcast frequency (kHz)": 518,
   "NAVTEX CRS name": "Hong Kong",
   "NAVTEX CRS identifier": "L",
   "Country": "China",
   "Latitude": "22° 13' N",
   "Longitude": "114° 15' E",
   "Broadcast range (NM)": "250",
   "Transmission times (All in UTC)": "0150, 0550, 0950, 1350, 1750, 2150",
   "Broadcast language": "English"
 },
 {
   "NAVAREA": "XI",
   "Broadcast frequency (kHz)": 518,
   "NAVTEX CRS name": "Sanya",
   "NAVTEX CRS identifier": "M",
   "Country": "China",
   "Latitude": "18° 14' N",
   "Longitude": "109° 30' E",
   "Broadcast range (NM)": "250",
   "Transmission times (All in UTC)": "0200, 0600, 1000, 1400, 1800, 2200",
   "Broadcast language": "English, Chinese"
 },
 {
   "NAVAREA": "XI",
   "Broadcast frequency (kHz)": 518,
   "NAVTEX CRS name": "Guangzhou",
   "NAVTEX CRS identifier": "N",
   "Country": "China",
   "Latitude": "23° 09' N",
   "Longitude": "113° 29' E",
   "Broadcast range (NM)": "250",
   "Transmission times (All in UTC)": "0210, 0610, 1010, 1410, 1810, 2210",
   "Broadcast language": "English, Chinese"
 },
 {
   "NAVAREA": "XI",
   "Broadcast frequency (kHz)": 518,
   "NAVTEX CRS name": "Fuzhou",
   "NAVTEX CRS identifier": "O",
   "Country": "China",
   "Latitude": "26° 02' N",
   "Longitude": "119° 18' E",
   "Broadcast range (NM)": "250",
   "Transmission times (All in UTC)": "0220, 0620, 1020, 1420, 1820, 2220",
   "Broadcast language": "English"
 },
 {
   "NAVAREA": "XI",
   "Broadcast frequency (kHz)": 518,
   "NAVTEX CRS name": "Lintou",
   "NAVTEX CRS identifier": "P",
   "Country": "Taiwan",
   "Latitude": "23° 33' N",
   "Longitude": "119° 38' E",
   "Broadcast range (NM)": "350",
   "Transmission times (All in UTC)": "0230, 1030, 1830",
   "Broadcast language": "English"
 },
 {
   "NAVAREA": "XI",
   "Broadcast frequency (kHz)": 518,
   "NAVTEX CRS name": "Yenliaoken",
   "NAVTEX CRS identifier": "P",
   "Country": "Taiwan",
   "Latitude": "23° 54' N",
   "Longitude": "121° 36' E",
   "Broadcast range (NM)": "350",
   "Transmission times (All in UTC)": "0630, 1430, 2230",
   "Broadcast language": "English"
 },
 {
   "NAVAREA": "XI",
   "Broadcast frequency (kHz)": 518,
   "NAVTEX CRS name": "Shanghai",
   "NAVTEX CRS identifier": "Q",
   "Country": "China",
   "Latitude": "31° 07' N",
   "Longitude": "121° 33' E",
   "Broadcast range (NM)": "250",
   "Transmission times (All in UTC)": "0240, 0640, 1040, 1440, 1840, 2240",
   "Broadcast language": "English"
 },
 {
   "NAVAREA": "XI",
   "Broadcast frequency (kHz)": 518,
   "NAVTEX CRS name": "Dalian",
   "NAVTEX CRS identifier": "R",
   "Country": "China",
   "Latitude": "38° 52' N",
   "Longitude": "121° 31' E",
   "Broadcast range (NM)": "250",
   "Transmission times (All in UTC)": "0250, 0650, 1050, 1450, 1850, 2250",
   "Broadcast language": "English"
 },
 {
   "NAVAREA": "XI",
   "Broadcast frequency (kHz)": 518,
   "NAVTEX CRS name": "Sandakan",
   "NAVTEX CRS identifier": "S",
   "Country": "Malaysia",
   "Latitude": "05° 54' N",
   "Longitude": "118° 00' E",
   "Broadcast range (NM)": "350",
   "Transmission times (All in UTC)": "0300, 0700, 1100, 1500, 1900, 2300",
   "Broadcast language": "English"
 },
 {
   "NAVAREA": "XI",
   "Broadcast frequency (kHz)": 518,
   "NAVTEX CRS name": "Miri",
   "NAVTEX CRS identifier": "T",
   "Country": "Malaysia",
   "Latitude": "04° 28' N",
   "Longitude": "114° 01' E",
   "Broadcast range (NM)": "350",
   "Transmission times (All in UTC)": "0310, 0710, 1110, 1510, 1910, 2310",
   "Broadcast language": "English"
 },
 {
   "NAVAREA": "XI",
   "Broadcast frequency (kHz)": 518,
   "NAVTEX CRS name": "Penang",
   "NAVTEX CRS identifier": "U",
   "Country": "Malaysia",
   "Latitude": "05° 25' N",
   "Longitude": "100° 24' E",
   "Broadcast range (NM)": "350",
   "Transmission times (All in UTC)": "0320, 0720, 1120, 1520, 1920, 2320",
   "Broadcast language": "English"
 },
 {
   "NAVAREA": "XI",
   "Broadcast frequency (kHz)": 518,
   "NAVTEX CRS name": "Guam",
   "NAVTEX CRS identifier": "V",
   "Country": "Guam",
   "Latitude": "13° 29' N",
   "Longitude": "144° 50' E",
   "Broadcast range (NM)": "100",
   "Transmission times (All in UTC)": "0100, 0500, 0900, 1300, 1700, 2100",
   "Broadcast language": "English"
 },
 {
   "NAVAREA": "XI",
   "Broadcast frequency (kHz)": 518,
   "NAVTEX CRS name": "Chukpyon",
   "NAVTEX CRS identifier": "V",
   "Country": "South Korea",
   "Latitude": "37° 03' N",
   "Longitude": "129° 26' E",
   "Broadcast range (NM)": "200",
   "Transmission times (All in UTC)": "0330, 0730, 1130, 1530, 1930, 2330",
   "Broadcast language": "English"
 },
 {
   "NAVAREA": "XI",
   "Broadcast frequency (kHz)": 518,
   "NAVTEX CRS name": "Pyonsan",
   "NAVTEX CRS identifier": "W",
   "Country": "South Korea",
   "Latitude": "35° 36' N",
   "Longitude": "126° 29' E",
   "Broadcast range (NM)": "200",
   "Transmission times (All in UTC)": "0340, 0740, 1140, 1540, 1940, 2340",
   "Broadcast language": "English"
 },
 {
   "NAVAREA": "XI",
   "Broadcast frequency (kHz)": 518,
   "NAVTEX CRS name": "Ho Chi Minh-Ville",
   "NAVTEX CRS identifier": "X",
   "Country": "Vietnam",
   "Latitude": "10° 47' N",
   "Longitude": "106° 40' E",
   "Broadcast range (NM)": "400",
   "Transmission times (All in UTC)": "0350, 0750, 1150, 1550, 1950, 2350",
   "Broadcast language": "English"
 },
 {
   "NAVAREA": "XI",
   "Broadcast frequency (kHz)": 490,
   "NAVTEX CRS name": "Chukpyon",
   "NAVTEX CRS identifier": "J",
   "Country": "South Korea",
   "Latitude": "37° 03' N",
   "Longitude": "129° 26' E",
   "Broadcast range (NM)": "200",
   "Transmission times (All in UTC)": "0130, 0530, 0930, 1330, 1730, 2130",
   "Broadcast language": "Korean"
 },
 {
   "NAVAREA": "XI",
   "Broadcast frequency (kHz)": 490,
   "NAVTEX CRS name": "Pyonsan",
   "NAVTEX CRS identifier": "K",
   "Country": "South Korea",
   "Latitude": "35° 36' N",
   "Longitude": "126° 29' E",
   "Broadcast range (NM)": "200",
   "Transmission times (All in UTC)": "0140, 0540, 0940, 1340, 1740, 2140",
   "Broadcast language": "Korean"
 },
 {
   "NAVAREA": "XI",
   "Broadcast frequency (kHz)": 490,
   "NAVTEX CRS name": "Lintou",
   "NAVTEX CRS identifier": "V",
   "Country": "Taiwan",
   "Latitude": "23° 33' N",
   "Longitude": "119° 38' E",
   "Broadcast range (NM)": "350",
   "Transmission times (All in UTC)": "0330, 0730, 1130, 1530, 1930, 2330",
   "Broadcast language": "Chinese"
 },
 {
   "NAVAREA": "XI",
   "Broadcast frequency (kHz)": 490,
   "NAVTEX CRS name": "Yenliaoken",
   "NAVTEX CRS identifier": "X",
   "Country": "Taiwan",
   "Latitude": "23° 54' N",
   "Longitude": "121° 36' E",
   "Broadcast range (NM)": "350",
   "Transmission times (All in UTC)": "0350, 0750, 1150, 1550, 1950, 2350",
   "Broadcast language": "Chinese"
 },
 {
   "NAVAREA": "XI",
   "Broadcast frequency (kHz)": 424,
   "NAVTEX CRS name": "Naha",
   "NAVTEX CRS identifier": "G",
   "Country": "Japan",
   "Latitude": "26° 05' N",
   "Longitude": "127° 40' E",
   "Broadcast range (NM)": "400",
   "Transmission times (All in UTC)": "0000, 0400, 0800, 1200, 1600, 2000",
   "Broadcast language": "Japanese"
 },
 {
   "NAVAREA": "XI",
   "Broadcast frequency (kHz)": 424,
   "NAVTEX CRS name": "Moji",
   "NAVTEX CRS identifier": "H",
   "Country": "Japan",
   "Latitude": "34° 01' N",
   "Longitude": "130° 56' E",
   "Broadcast range (NM)": "400",
   "Transmission times (All in UTC)": "0017, 0417, 0817, 1217, 1617, 2017",
   "Broadcast language": "Japanese"
 },
 {
   "NAVAREA": "XI",
   "Broadcast frequency (kHz)": 424,
   "NAVTEX CRS name": "Yokohama",
   "NAVTEX CRS identifier": "I",
   "Country": "Japan",
   "Latitude": "35° 14' N",
   "Longitude": "139° 55' E",
   "Broadcast range (NM)": "400",
   "Transmission times (All in UTC)": "0034, 0434, 0834, 1234, 1634, 2034",
   "Broadcast language": "Japanese"
 },
 {
   "NAVAREA": "XI",
   "Broadcast frequency (kHz)": 424,
   "NAVTEX CRS name": "Otaru",
   "NAVTEX CRS identifier": "J",
   "Country": "Japan",
   "Latitude": "43° 19' N",
   "Longitude": "140° 27' E",
   "Broadcast range (NM)": "400",
   "Transmission times (All in UTC)": "0051, 0451, 0851, 1251, 1651, 2051",
   "Broadcast language": "Japanese"
 },
 {
   "NAVAREA": "XI",
   "Broadcast frequency (kHz)": 424,
   "NAVTEX CRS name": "Otaru",
   "NAVTEX CRS identifier": "K",
   "Country": "Japan",
   "Latitude": "42° 57' N",
   "Longitude": "144° 36' E",
   "Broadcast range (NM)": "400",
   "Transmission times (All in UTC)": "0108, 0508, 0908, 1308, 1708, 2108",
   "Broadcast language": "Japanese"
 },
 {
   "NAVAREA": "XI",
   "Broadcast frequency (kHz)": 4209.5,
   "NAVTEX CRS name": "Chi-Lung (Keelung)",
   "NAVTEX CRS identifier": "P",
   "Country": "Taiwan",
   "Latitude": "25° 08' N",
   "Longitude": "121° 45' E",
   "Broadcast range (NM)": "540",
   "Transmission times (All in UTC)": "0230, 1030, 1830",
   "Broadcast language": "English"
 },
 {
   "NAVAREA": "XI",
   "Broadcast frequency (kHz)": 4209.5,
   "NAVTEX CRS name": "Linyuan",
   "NAVTEX CRS identifier": "P",
   "Country": "Taiwan",
   "Latitude": "22° 29' N",
   "Longitude": "120° 25' E",
   "Broadcast range (NM)": "540",
   "Transmission times (All in UTC)": "0630, 1430, 2230",
   "Broadcast language": "English"
 },
 {
   "NAVAREA": "XI",
   "Broadcast frequency (kHz)": 4209.5,
   "NAVTEX CRS name": "Chi-Lung (Keelung)",
   "NAVTEX CRS identifier": "V",
   "Country": "Taiwan",
   "Latitude": "25° 08' N",
   "Longitude": "121° 45' E",
   "Broadcast range (NM)": "540",
   "Transmission times (All in UTC)": "0330, 0730, 1130, 1530, 1930, 2330",
   "Broadcast language": "Chinese"
 },
 {
   "NAVAREA": "XI",
   "Broadcast frequency (kHz)": 4209.5,
   "NAVTEX CRS name": "Hai Phong",
   "NAVTEX CRS identifier": "W",
   "Country": "Vietnam",
   "Latitude": "20° 43' N",
   "Longitude": "106° 44' E",
   "Broadcast range (NM)": "400",
   "Transmission times (All in UTC)": "0340, 0740, 1140, 1540, 1940, 2340",
   "Broadcast language": "English"
 },
 {
   "NAVAREA": "XI",
   "Broadcast frequency (kHz)": 4209.5,
   "NAVTEX CRS name": "Linyuan",
   "NAVTEX CRS identifier": "X",
   "Country": "Taiwan",
   "Latitude": "22° 29' N",
   "Longitude": "120° 25' E",
   "Broadcast range (NM)": "540",
   "Transmission times (All in UTC)": "0350, 0750, 1150, 1550, 1950, 2350",
   "Broadcast language": "Chinese"
 },
 {
   "NAVAREA": "XII",
   "Broadcast frequency (kHz)": 518,
   "NAVTEX CRS name": "San Francisco (Point Reyes)",
   "NAVTEX CRS identifier": "C",
   "Country": "USA",
   "Latitude": "37° 55' N",
   "Longitude": "122° 42' W",
   "Broadcast range (NM)": "350",
   "Transmission times (All in UTC)": "0000, 0400, 0800, 1200, 1600, 2000",
   "Broadcast language": "English"
 },
 {
   "NAVAREA": "XII",
   "Broadcast frequency (kHz)": 518,
   "NAVTEX CRS name": "Prince Rupert",
   "NAVTEX CRS identifier": "D",
   "Country": "Canada",
   "Latitude": "54° 18' N",
   "Longitude": "130° 25' W",
   "Broadcast range (NM)": "300",
   "Transmission times (All in UTC)": "0030, 0430, 0830, 1230, 1630, 2030",
   "Broadcast language": "English"
 },
 {
   "NAVAREA": "XII",
   "Broadcast frequency (kHz)": 518,
   "NAVTEX CRS name": "Tofino",
   "NAVTEX CRS identifier": "H",
   "Country": "Canada",
   "Latitude": "48° 56' N",
   "Longitude": "125° 32' W",
   "Broadcast range (NM)": "300",
   "Transmission times (All in UTC)": "0110, 0510, 0910, 1310, 1710, 2110",
   "Broadcast language": "English"
 },
 {
   "NAVAREA": "XII",
   "Broadcast frequency (kHz)": 518,
   "NAVTEX CRS name": "Kodiak (east of)",
   "NAVTEX CRS identifier": "J",
   "Country": "Alaska",
   "Latitude": "57° 46' N",
   "Longitude": "152° 34' W",
   "Broadcast range (NM)": "200",
   "Transmission times (All in UTC)": "0300, 0700, 1100, 1500, 1900, 2300",
   "Broadcast language": "English"
 },
 {
   "NAVAREA": "XII",
   "Broadcast frequency (kHz)": 518,
   "NAVTEX CRS name": "Ayora",
   "NAVTEX CRS identifier": "L",
   "Country": "Equador",
   "Latitude": "00° 45' S",
   "Longitude": "90° 19' W",
   "Broadcast range (NM)": "250-400",
   "Transmission times (All in UTC)": "0150, 0550, 0950, 1350, 1750, 2150",
   "Broadcast language": "English"
 },
 {
   "NAVAREA": "XII",
   "Broadcast frequency (kHz)": 518,
   "NAVTEX CRS name": "Honolulu",
   "NAVTEX CRS identifier": "O",
   "Country": "Hawaii",
   "Latitude": "21° 22' N",
   "Longitude": "158° 09' W",
   "Broadcast range (NM)": "350",
   "Transmission times (All in UTC)": "0040, 0440, 0840, 1240, 1640, 2040",
   "Broadcast language": "English"
 },
 {
   "NAVAREA": "XII",
   "Broadcast frequency (kHz)": 518,
   "NAVTEX CRS name": "Long Beach (Cambria)",
   "NAVTEX CRS identifier": "Q",
   "Country": "USA",
   "Latitude": "35° 31' N",
   "Longitude": "121° 03' W",
   "Broadcast range (NM)": "350",
   "Transmission times (All in UTC)": "0045, 0445, 0845, 1245, 1645, 2045",
   "Broadcast language": "English"
 },
 {
   "NAVAREA": "XII",
   "Broadcast frequency (kHz)": 518,
   "NAVTEX CRS name": "Astoria",
   "NAVTEX CRS identifier": "W",
   "Country": "USA",
   "Latitude": "46° 10' N",
   "Longitude": "123° 49' W",
   "Broadcast range (NM)": "216",
   "Transmission times (All in UTC)": "0130, 0530, 0930, 1330, 1730, 2130",
   "Broadcast language": "English"
 },
 {
   "NAVAREA": "XII",
   "Broadcast frequency (kHz)": 518,
   "NAVTEX CRS name": "Kodiak (west of)",
   "NAVTEX CRS identifier": "X",
   "Country": "Alaska",
   "Latitude": "57° 46' N",
   "Longitude": "152° 34' W",
   "Broadcast range (NM)": "200",
   "Transmission times (All in UTC)": "0340, 0740, 1140, 1540, 1940, 2340",
   "Broadcast language": "English"
 },
 {
   "NAVAREA": "XII",
   "Broadcast frequency (kHz)": 490,
   "NAVTEX CRS name": "Ayora",
   "NAVTEX CRS identifier": "A",
   "Country": "Equador",
   "Latitude": "00° 45' S",
   "Longitude": "90° 19' W",
   "Broadcast range (NM)": "250-400",
   "Transmission times (All in UTC)": "0000, 0400, 0800, 1200, 1600, 2000",
   "Broadcast language": "Spanish"
 },
 {
   "NAVAREA": "XIII",
   "Broadcast frequency (kHz)": 518,
   "NAVTEX CRS name": "Vladivostok",
   "NAVTEX CRS identifier": "A",
   "Country": "Russia",
   "Latitude": "43° 23' N",
   "Longitude": "131° 54' E",
   "Broadcast range (NM)": "280",
   "Transmission times (All in UTC)": "0000, 0400, 0800, 1200, 1600, 2000",
   "Broadcast language": "English"
 },
 {
   "NAVAREA": "XIII",
   "Broadcast frequency (kHz)": 518,
   "NAVTEX CRS name": "Kholmsk",
   "NAVTEX CRS identifier": "B",
   "Country": "Russia",
   "Latitude": "47° 02' N",
   "Longitude": "142° 03' E",
   "Broadcast range (NM)": "300",
   "Transmission times (All in UTC)": "0010, 0410, 0810, 1210, 1610, 2010",
   "Broadcast language": "English"
 },
 {
   "NAVAREA": "XIII",
   "Broadcast frequency (kHz)": 518,
   "NAVTEX CRS name": "Petropavlosk",
   "NAVTEX CRS identifier": "C",
   "Country": "Russia",
   "Latitude": "53° 15' N",
   "Longitude": "158° 25' E",
   "Broadcast range (NM)": "280",
   "Transmission times (All in UTC)": "0020, 0420, 0820, 1220, 1620, 2020",
   "Broadcast language": "English"
 },
 {
   "NAVAREA": "XIII",
   "Broadcast frequency (kHz)": 518,
   "NAVTEX CRS name": "Magadan",
   "NAVTEX CRS identifier": "D",
   "Country": "Russia",
   "Latitude": "59° 41' N",
   "Longitude": "150° 09' E",
   "Broadcast range (NM)": "120",
   "Transmission times (All in UTC)": "0030, 0430, 0830, 1230, 1630, 2030",
   "Broadcast language": "English"
 },
 {
   "NAVAREA": "XIII",
   "Broadcast frequency (kHz)": 518,
   "NAVTEX CRS name": "Okhotsk",
   "NAVTEX CRS identifier": "G",
   "Country": "Russia",
   "Latitude": "59° 22' N",
   "Longitude": "143° 12' E",
   "Broadcast range (NM)": "300",
   "Transmission times (All in UTC)": "0100, 0500, 0900, 1300, 1700, 2100",
   "Broadcast language": "English"
 },
 {
   "NAVAREA": "XIII",
   "Broadcast frequency (kHz)": 518,
   "NAVTEX CRS name": "Astrakhan",
   "NAVTEX CRS identifier": "W",
   "Country": "Russia",
   "Latitude": "45° 47' N",
   "Longitude": "47° 33' E",
   "Broadcast range (NM)": "250",
   "Transmission times (All in UTC)": "0340, 0740, 1140, 1540, 1940, 2340",
   "Broadcast language": "English"
 },
 {
   "NAVAREA": "XV",
   "Broadcast frequency (kHz)": 518,
   "NAVTEX CRS name": "Antofagasta",
   "NAVTEX CRS identifier": "A",
   "Country": "Chile",
   "Latitude": "23° 40' S",
   "Longitude": "70° 25' W",
   "Broadcast range (NM)": "300",
   "Transmission times (All in UTC)": "0400, 1200, 2000",
   "Broadcast language": "English"
 },
 {
   "NAVAREA": "XV",
   "Broadcast frequency (kHz)": 518,
   "NAVTEX CRS name": "Valparaiso",
   "NAVTEX CRS identifier": "B",
   "Country": "Chile",
   "Latitude": "32° 48' S",
   "Longitude": "71° 29' W",
   "Broadcast range (NM)": "300",
   "Transmission times (All in UTC)": "0410, 1210, 2010",
   "Broadcast language": "English"
 },
 {
   "NAVAREA": "XV",
   "Broadcast frequency (kHz)": 518,
   "NAVTEX CRS name": "Talcahuano",
   "NAVTEX CRS identifier": "C",
   "Country": "Chile",
   "Latitude": "36° 42' S",
   "Longitude": "73° 06' W",
   "Broadcast range (NM)": "300",
   "Transmission times (All in UTC)": "0420, 1220, 2020",
   "Broadcast language": "English"
 },
 {
   "NAVAREA": "XV",
   "Broadcast frequency (kHz)": 518,
   "NAVTEX CRS name": "Puerto Montt",
   "NAVTEX CRS identifier": "D",
   "Country": "Chile",
   "Latitude": "41° 29' S",
   "Longitude": "72° 57' W",
   "Broadcast range (NM)": "300",
   "Transmission times (All in UTC)": "0430, 1230, 2030",
   "Broadcast language": "English"
 },
 {
   "NAVAREA": "XV",
   "Broadcast frequency (kHz)": 518,
   "NAVTEX CRS name": "Magallenes",
   "NAVTEX CRS identifier": "E",
   "Country": "Chile",
   "Latitude": "52° 56' S",
   "Longitude": "70° 54' W",
   "Broadcast range (NM)": "300",
   "Transmission times (All in UTC)": "0440, 1240, 2040",
   "Broadcast language": "English"
 },
 {
   "NAVAREA": "XV",
   "Broadcast frequency (kHz)": 518,
   "NAVTEX CRS name": "Isla de Pascua",
   "NAVTEX CRS identifier": "F",
   "Country": "Easter Island",
   "Latitude": "27° 09' S",
   "Longitude": "109° 23' W",
   "Broadcast range (NM)": "300",
   "Transmission times (All in UTC)": "0450, 1250, 2050",
   "Broadcast language": "English"
 },
 {
   "NAVAREA": "XV",
   "Broadcast frequency (kHz)": 518,
   "NAVTEX CRS name": "Isla de Pascua",
   "NAVTEX CRS identifier": "G",
   "Country": "Easter Island",
   "Latitude": "27° 09' S",
   "Longitude": "109° 23' W",
   "Broadcast range (NM)": "300",
   "Transmission times (All in UTC)": "0450, 0850, 1650",
   "Broadcast language": "Spanish"
 },
 {
   "NAVAREA": "XV",
   "Broadcast frequency (kHz)": 518,
   "NAVTEX CRS name": "Antofagasta",
   "NAVTEX CRS identifier": "H",
   "Country": "Chile",
   "Latitude": "23° 40' S",
   "Longitude": "70° 25' W",
   "Broadcast range (NM)": "300",
   "Transmission times (All in UTC)": "0000, 0800, 1600",
   "Broadcast language": "Spanish"
 },
 {
   "NAVAREA": "XV",
   "Broadcast frequency (kHz)": 518,
   "NAVTEX CRS name": "Valparaiso",
   "NAVTEX CRS identifier": "I",
   "Country": "Chile",
   "Latitude": "32° 48' S",
   "Longitude": "71° 29' W",
   "Broadcast range (NM)": "300",
   "Transmission times (All in UTC)": "0010, 0810, 1610",
   "Broadcast language": "Spanish"
 },
 {
   "NAVAREA": "XV",
   "Broadcast frequency (kHz)": 518,
   "NAVTEX CRS name": "Talcahuano",
   "NAVTEX CRS identifier": "J",
   "Country": "Chile",
   "Latitude": "36° 42' S",
   "Longitude": "73° 06' W",
   "Broadcast range (NM)": "300",
   "Transmission times (All in UTC)": "0020, 0820, 1620",
   "Broadcast language": "Spanish"
 },
 {
   "NAVAREA": "XV",
   "Broadcast frequency (kHz)": 518,
   "NAVTEX CRS name": "Puerto Montt",
   "NAVTEX CRS identifier": "K",
   "Country": "Chile",
   "Latitude": "41° 29' S",
   "Longitude": "72° 57' W",
   "Broadcast range (NM)": "300",
   "Transmission times (All in UTC)": "0030, 0830,1630",
   "Broadcast language": "Spanish"
 },
 {
   "NAVAREA": "XV",
   "Broadcast frequency (kHz)": 518,
   "NAVTEX CRS name": "Magallenes",
   "NAVTEX CRS identifier": "L",
   "Country": "Chile",
   "Latitude": "52° 56' S",
   "Longitude": "70° 54' W",
   "Broadcast range (NM)": "300",
   "Transmission times (All in UTC)": "0040, 0840, 1640",
   "Broadcast language": "Spanish"
 },
 {
   "NAVAREA": "XVI",
   "Broadcast frequency (kHz)": 518,
   "NAVTEX CRS name": "Paita",
   "NAVTEX CRS identifier": "S",
   "Country": "Peru",
   "Latitude": "05° 05' S",
   "Longitude": "81° 07' W",
   "Broadcast range (NM)": "400",
   "Transmission times (All in UTC)": "0300, 0700, 1100, 1500, 1900, 2300",
   "Broadcast language": "English, Spanish"
 },
 {
   "NAVAREA": "XVI",
   "Broadcast frequency (kHz)": 518,
   "NAVTEX CRS name": "Callao",
   "NAVTEX CRS identifier": "U",
   "Country": "Peru",
   "Latitude": "12° 03' S",
   "Longitude": "77° 09' W",
   "Broadcast range (NM)": "400",
   "Transmission times (All in UTC)": "0320, 0720, 1120, 1520, 1920, 2320",
   "Broadcast language": "English, Spanish"
 },
 {
   "NAVAREA": "XVI",
   "Broadcast frequency (kHz)": 518,
   "NAVTEX CRS name": "Mollendo",
   "NAVTEX CRS identifier": "W",
   "Country": "Peru",
   "Latitude": "17° 01' S",
   "Longitude": "72° 01' W",
   "Broadcast range (NM)": "400",
   "Transmission times (All in UTC)": "0340, 0740, 1140, 1540, 1940, 2340",
   "Broadcast language": "English, Spanish"
 }
]
